{
  "$schema": "http://json-schema.org/draft-07/schema#",
  "title": "Pulse",
  "description": "A quantum entity representing a wave of subjective experience. This is the atomic unit of emotional memory (The Wave).",
  "x-familiar-kind": "entity",
  "allOf": [
    { "$ref": "../architecture/meta/PhysicalEntity.meta.schema.json" }
  ],
  "properties": {
    "metadata": {
      "additionalProperties": {
        "type": "string"
      },
      "type": "object"
    },
    "state_type": {
      "$ref": "../types/InternalStateType.schema.json"
    },
    "text": {
      "type": "string"
    }
  },
  "required": [
    "metadata",
    "state_type",
    "text"
  ],
  "type": "object",
  "x-familiar-persistence": {
    "profile": "timescaledb",
    "hypertable": true,
    "table": "pulses",
    "primary_key": ["id", "t_coord"],
    "partition_column": "t_coord",
    "indexes": [
      "tenant_id",
      "t_coord",
      "state_type"
    ]
  },
  "x-familiar-service": {
    "$ref": "../infrastructure/nodes/familiar-daemon.node.json"
  },
  "x-familiar-composition": {
    "physics": [
      "amplitude",
      "energy",
      "position",
      "temperature",
      "velocity"
    ],
    "note": "identity fields kept direct (typed IDs)"
  }
}
