{
  "$schema": "http://json-schema.org/draft-07/schema#",
  "definitions": {
    "TraceKind": {
      "description": "Types of trace events",
      "oneOf": [
        {
          "description": "Agent thinking/reasoning step",
          "enum": [
            "step"
          ],
          "type": "string"
        },
        {
          "description": "Tool invocation",
          "enum": [
            "tool"
          ],
          "type": "string"
        },
        {
          "description": "Routing decision between agents",
          "enum": [
            "route"
          ],
          "type": "string"
        },
        {
          "description": "Safe log message",
          "enum": [
            "log"
          ],
          "type": "string"
        },
        {
          "description": "Response token stream (for streaming responses)",
          "enum": [
            "token"
          ],
          "type": "string"
        },
        {
          "description": "Final result",
          "enum": [
            "result"
          ],
          "type": "string"
        }
      ]
    },
    "TracePayload": {
      "description": "Trace payload - sanitized for UI consumption",
      "properties": {
        "agent": {
          "description": "Agent that produced this trace (concierge, classifier, etc.)",
          "type": [
            "string",
            "null"
          ]
        },
        "duration_ms": {
          "description": "Duration in milliseconds (if status == Succeeded or Failed)",
          "format": "uint64",
          "minimum": 0.0,
          "type": [
            "integer",
            "null"
          ]
        },
        "message": {
          "description": "Human-readable message",
          "type": "string"
        },
        "tokens": {
          "description": "Response tokens (if kind == Token)",
          "type": [
            "string",
            "null"
          ]
        },
        "tool_args": {
          "description": "Tool arguments (redacted/summarized)"
        },
        "tool_name": {
          "description": "Tool name (if kind == Tool)",
          "type": [
            "string",
            "null"
          ]
        },
        "tool_result": {
          "description": "Tool result (summary only, not full output)",
          "type": [
            "string",
            "null"
          ]
        }
      },
      "required": [
        "message"
      ],
      "type": "object"
    },
    "TraceStatus": {
      "description": "Status of a trace span",
      "oneOf": [
        {
          "description": "Span has started",
          "enum": [
            "started"
          ],
          "type": "string"
        },
        {
          "description": "Span completed successfully",
          "enum": [
            "succeeded"
          ],
          "type": "string"
        },
        {
          "description": "Span failed",
          "enum": [
            "failed"
          ],
          "type": "string"
        },
        {
          "description": "Span was skipped",
          "enum": [
            "skipped"
          ],
          "type": "string"
        }
      ]
    }
  },
  "description": "Trace envelope for UI streaming\n\nNote: This is a legacy type. Prefer using EnvelopeV1 with Trace payload for new code. EnvelopeV1 uses native Protobuf serialization for better performance.",
  "properties": {
    "course_id": {
      "description": "Course (interaction) this trace belongs to",
      "format": "uuid",
      "type": "string"
    },
    "kind": {
      "allOf": [
        {
          "$ref": "#/definitions/TraceKind"
        }
      ],
      "description": "Type of trace"
    },
    "occurred_at": {
      "description": "When this trace was emitted",
      "format": "date-time",
      "type": "string"
    },
    "parent_span_id": {
      "description": "Parent span (for hierarchy)",
      "type": [
        "string",
        "null"
      ]
    },
    "payload": {
      "allOf": [
        {
          "$ref": "#/definitions/TracePayload"
        }
      ],
      "description": "The actual payload (sanitized for UI)"
    },
    "seq": {
      "description": "Monotonic sequence number per-course (for ordering and backfill)",
      "format": "uint64",
      "minimum": 0.0,
      "type": "integer"
    },
    "span_id": {
      "description": "Span identifier for this trace unit",
      "type": "string"
    },
    "status": {
      "allOf": [
        {
          "$ref": "#/definitions/TraceStatus"
        }
      ],
      "description": "Status of this trace unit"
    }
  },
  "required": [
    "course_id",
    "kind",
    "occurred_at",
    "payload",
    "seq",
    "span_id",
    "status"
  ],
  "title": "TraceEnvelope",
  "type": "object"
}